{
  "Foreground:Active": 4290493371,
  "HighlightedText:Active": 4294967295,
  "Mid:Active": 4281150765,
  "WindowText:Normal": 4290493371,
  "Window:Disabled": 4282664004,
  "AlternateBase:Inactive": 4281216558,
  "Midlight:Normal": 4281808695,
  "HighlightedText:Inactive": 4294967295,
  "Text:Disabled": 4285098345,
  "Midlight:Disabled": 4281808695,
  "Midlight:Inactive": 4281808695,
  "Highlight:Disabled": 4283590260,
  "Base:Disabled": 4281019179,
  "Window:Active": 4282664004,
  "Background:Inactive": 4282664004,
  "AlternateBase:Disabled": 4281216558,
  "Button:Inactive": 4284308829,
  "AlternateBase:Active": 4281216558,
  "LinkVisited:Active": 4283570315,
  "ToolTipBase:Inactive": 4294967260,
  "Dark:Inactive": 4280624421,
  "LinkVisited:Inactive": 4283570315,
  "Dark:Disabled": 4280624421,
  "Light:Inactive": 4284572001,
  "ButtonText:Inactive": 4293848814,
  "Dark:Active": 4280624421,
  "Light:Disabled": 4284572001,
  "Button:Disabled": 4283124555,
  "Shadow:Inactive": 4278190080,
  "ToolTipBase:Disabled": 4294967260,
  "BrightText:Inactive": 4280624421,
  "ToolTipBase:Active": 4294967260,
  "Highlight:Active": 4283598246,
  "BrightText:Disabled": 4294967295,
  "Highlight:Inactive": 4283598246,
  "ToolTipText:Active": 4278190080,
  "Light:Active": 4284572001,
  "Button:Active": 4284308829,
  "ButtonText:Disabled": 4286611584,
  "HighlightedText:Normal": 4294967295,
  "Base:Inactive": 4281019179,
  "BrightText:Active": 4280624421,
  "Highlight:Normal": 4283598246,
  "AlternateBase:Normal": 4281216558,
  "Dark:Normal": 4280624421,
  "Window:Inactive": 4282664004,
  "LinkVisited:Normal": 4283570315,
  "Link:Normal": 4278190318,
  "Base:Active": 4281019179,
  "Mid:Inactive": 4281150765,
  "Foreground:Disabled": 4286611584,
  "Text:Normal": 4291348680,
  "Link:Inactive": 4278190318,
  "ButtonText:Normal": 4293848814,
  "WindowText:Inactive": 4290493371,
  "ToolTipBase:Normal": 4294967260,
  "ToolTipText:Inactive": 4278190080,
  "WindowText:Disabled": 4286611584,
  "ToolTipText:Normal": 4278190080,
  "Midlight:Active": 4281808695,
  "ButtonText:Active": 4293848814,
  "BrightText:Normal": 4280624421,
  "Text:Active": 4291348680,
  "Mid:Normal": 4281150765,
  "WindowText:Active": 4290493371,
  "Base:Normal": 4281019179,
  "Background:Normal": 4282664004,
  "Mid:Disabled": 4281150765,
  "Background:Disabled": 4282664004,
  "Link:Disabled": 4278190318,
  "Window:Normal": 4282664004,
  "Shadow:Active": 4278190080,
  "Text:Inactive": 4291348680,
  "Button:Normal": 4284308829,
  "Light:Normal": 4284572001,
  "Link:Active": 4278190318,
  "Background:Active": 4282664004,
  "HighlightedText:Disabled": 4294967295,
  "Shadow:Disabled": 4278190080,
  "ToolTipText:Disabled": 4278190080,
  "Foreground:Normal": 4290493371,
  "LinkVisited:Disabled": 4283570315,
  "Shadow:Normal": 4278190080,
  "Foreground:Inactive": 4290493371
}